ga4gh_dos_schemas-0.2.0-py2.7-nspkg.pth
ga4gh/dos/__init__.py
ga4gh/dos/client.py
ga4gh/dos/controllers.py
ga4gh/dos/data_object_service.swagger.yaml
ga4gh/dos/data_objects_service.swagger.json
ga4gh/dos/server.py
ga4gh_dos_schemas-0.2.0.dist-info/DESCRIPTION.rst
ga4gh_dos_schemas-0.2.0.dist-info/METADATA
ga4gh_dos_schemas-0.2.0.dist-info/RECORD
ga4gh_dos_schemas-0.2.0.dist-info/WHEEL
ga4gh_dos_schemas-0.2.0.dist-info/entry_points.txt
ga4gh_dos_schemas-0.2.0.dist-info/metadata.json
ga4gh_dos_schemas-0.2.0.dist-info/namespace_packages.txt
ga4gh_dos_schemas-0.2.0.dist-info/top_level.txt
ga4gh_dos_schemas-0.2.0.dist-info/zip-safe
