Metadata-Version: 2.0
Name: ga4gh-dos-schemas
Version: 0.2.0
Summary: GA4GH Data Object Service Schemas
Home-page: https://github.com/ga4gh/data-object-schemas
Author: Global Alliance for Genomics and Health
Author-email: theglobalalliance@genomicsandhealth.org
License: Apache License 2.0
Keywords: genomics
Platform: UNKNOWN
Classifier: Development Status :: 3 - Alpha
Classifier: Intended Audience :: Science/Research
Classifier: License :: OSI Approved :: Apache Software License
Classifier: Natural Language :: English
Classifier: Programming Language :: Python :: 2.7
Classifier: Topic :: Scientific/Engineering :: Bio-Informatics
Requires-Dist: bravado
Requires-Dist: bravado-core
Requires-Dist: connexion
Requires-Dist: flask-cors
Requires-Dist: rfc3987
Requires-Dist: strict-rfc3339
Requires-Dist: webcolors
